aa_theme_slate/__init__.py
aa_theme_slate/apps.py
aa_theme_slate/images/aa_theme_slate.jpg
aa_theme_slate/static/aa_theme_slate/theme/aav3/css/aa-theme-slate.css
aa_theme_slate/static/aa_theme_slate/theme/aav3/css/aa-theme-slate.min.css
aa_theme_slate/static/aa_theme_slate/theme/aav3/css/aa-theme-slate.min.css.map
aa_theme_slate/static/aa_theme_slate/theme/aav3/css/community-app-fixes.css
aa_theme_slate/static/aa_theme_slate/theme/aav3/css/community-app-fixes.min.css
aa_theme_slate/static/aa_theme_slate/theme/aav3/css/community-app-fixes.min.css.map
aa_theme_slate/static/aa_theme_slate/theme/aav3/fonts/roboto/roboto-100-italic.woff
aa_theme_slate/static/aa_theme_slate/theme/aav3/fonts/roboto/roboto-100-italic.woff2
aa_theme_slate/static/aa_theme_slate/theme/aav3/fonts/roboto/roboto-100.woff
aa_theme_slate/static/aa_theme_slate/theme/aav3/fonts/roboto/roboto-100.woff2
aa_theme_slate/static/aa_theme_slate/theme/aav3/fonts/roboto/roboto-300-italic.woff
aa_theme_slate/static/aa_theme_slate/theme/aav3/fonts/roboto/roboto-300-italic.woff2
aa_theme_slate/static/aa_theme_slate/theme/aav3/fonts/roboto/roboto-300.woff
aa_theme_slate/static/aa_theme_slate/theme/aav3/fonts/roboto/roboto-300.woff2
aa_theme_slate/static/aa_theme_slate/theme/aav3/fonts/roboto/roboto-500-italic.woff
aa_theme_slate/static/aa_theme_slate/theme/aav3/fonts/roboto/roboto-500-italic.woff2
aa_theme_slate/static/aa_theme_slate/theme/aav3/fonts/roboto/roboto-500.woff
aa_theme_slate/static/aa_theme_slate/theme/aav3/fonts/roboto/roboto-500.woff2
aa_theme_slate/static/aa_theme_slate/theme/aav3/fonts/roboto/roboto-700-italic.woff
aa_theme_slate/static/aa_theme_slate/theme/aav3/fonts/roboto/roboto-700-italic.woff2
aa_theme_slate/static/aa_theme_slate/theme/aav3/fonts/roboto/roboto-700.woff
aa_theme_slate/static/aa_theme_slate/theme/aav3/fonts/roboto/roboto-700.woff2
aa_theme_slate/static/aa_theme_slate/theme/aav3/fonts/roboto/roboto-900-italic.woff
aa_theme_slate-2.4.1.dist-info/METADATA
aa_theme_slate-2.4.1.dist-info/WHEEL
aa_theme_slate-2.4.1.dist-info/licenses/LICENSE
aa_theme_slate-2.4.1.dist-info/RECORD
